campfirevalley/__init__.py
campfirevalley/auditor_workflow.py
campfirevalley/campfire.py
campfirevalley/cli.py
campfirevalley/config.py
campfirevalley/config_manager.py
campfirevalley/developer_campfires.py
campfirevalley/dock.py
campfirevalley/federation.py
campfirevalley/hierarchical_storage.py
campfirevalley/interfaces.py
campfirevalley/justice.py
campfirevalley/key_manager.py
campfirevalley/llm_campfire.py
campfirevalley/mcp.py
campfirevalley/models.py
campfirevalley/monitoring.py
campfirevalley/party_box.py
campfirevalley/routing.py
campfirevalley/security_scanner.py
campfirevalley/specialist_campfires.py
campfirevalley/vali.py
campfirevalley/valley.py
campfirevalley/campfires/__init__.py
campfirevalley/campfires/dockmaster.py
campfirevalley/campfires/justice.py
campfirevalley/campfires/sanitizer.py
campfirevalley/web/__init__.py
campfirevalley/web/api.py
campfirevalley/web/models.py
campfirevalley/web/server.py
campfirevalley/web/visualization.py
campfirevalley/web/static/index.html
campfirevalley/web/static/css/style.css
campfirevalley/web/static/img/camper_icon.svg
campfirevalley/web/static/img/campfire_icon.svg
campfirevalley/web/static/img/dock_icon.svg
campfirevalley/web/static/img/hex_bg.svg
campfirevalley/web/static/img/valley_icon.svg
campfirevalley/web/static/js/campfire-nodes.js
campfirevalley/web/static/js/gamification.js
campfirevalley/web/static/js/litegraph-integration.js
campfirevalley/web/static/js/litegraph.js
campfirevalley/web/static/js/main.js
campfirevalley/web/static/js/metrics.js
campfirevalley/web/static/js/visualization.js
campfirevalley-1.2.0.dist-info/METADATA
campfirevalley-1.2.0.dist-info/WHEEL
campfirevalley-1.2.0.dist-info/entry_points.txt
campfirevalley-1.2.0.dist-info/top_level.txt
campfirevalley-1.2.0.dist-info/RECORD
