Metadata-Version: 2.4
Name: campfirevalley
Version: 1.2.0
Summary: A distributed AI agent orchestration platform with visual LiteGraph interface
Home-page: https://github.com/MikeHibbert/pyCamperValley
Author: Mike Hibbert
Author-email: Mike Hibbert <mike@hibbertitsolutions.co.uk>
License: MIT
Project-URL: Homepage, https://github.com/yourusername/CampfireValley
Project-URL: Documentation, https://yourusername.github.io/CampfireValley
Project-URL: Repository, https://github.com/yourusername/CampfireValley.git
Project-URL: Bug Tracker, https://github.com/yourusername/CampfireValley/issues
Project-URL: Changelog, https://github.com/yourusername/CampfireValley/blob/main/CHANGELOG.md
Keywords: ai,agents,orchestration,distributed,litegraph,visualization
Classifier: Development Status :: 4 - Beta
Classifier: Intended Audience :: Developers
Classifier: License :: OSI Approved :: MIT License
Classifier: Operating System :: OS Independent
Classifier: Programming Language :: Python :: 3
Classifier: Programming Language :: Python :: 3.8
Classifier: Programming Language :: Python :: 3.9
Classifier: Programming Language :: Python :: 3.10
Classifier: Programming Language :: Python :: 3.11
Classifier: Programming Language :: Python :: 3.12
Classifier: Topic :: Software Development :: Libraries :: Python Modules
Classifier: Topic :: System :: Distributed Computing
Classifier: Topic :: Scientific/Engineering :: Artificial Intelligence
Requires-Python: >=3.8
Requires-Dist: fastapi>=0.104.0
Requires-Dist: uvicorn[standard]>=0.24.0
Requires-Dist: pydantic>=2.0.0
Requires-Dist: pyyaml>=6.0
Requires-Dist: aiofiles>=23.0.0
Requires-Dist: python-multipart>=0.0.6
Requires-Dist: jinja2>=3.1.0
Requires-Dist: click>=8.0.0
Requires-Dist: rich>=13.0.0
Requires-Dist: asyncio-mqtt>=0.16.0
Requires-Dist: websockets>=12.0
Requires-Dist: httpx>=0.25.0
Provides-Extra: dev
Requires-Dist: pytest>=7.0.0; extra == "dev"
Requires-Dist: pytest-asyncio>=0.21.0; extra == "dev"
Requires-Dist: pytest-cov>=4.0.0; extra == "dev"
Requires-Dist: black>=23.0.0; extra == "dev"
Requires-Dist: isort>=5.12.0; extra == "dev"
Requires-Dist: flake8>=6.0.0; extra == "dev"
Requires-Dist: mypy>=1.5.0; extra == "dev"
Provides-Extra: docs
Requires-Dist: mkdocs>=1.5.0; extra == "docs"
Requires-Dist: mkdocs-material>=9.0.0; extra == "docs"
Requires-Dist: mkdocstrings[python]>=0.23.0; extra == "docs"
Dynamic: author
Dynamic: home-page
Dynamic: requires-python
